haki_prawojazdycompl/__init__.py
haki_prawojazdycompl/skeleton.py
omijacz_timera/__init__.py
omijacz_timera/additional.py
omijacz_timera/automator.py
omijacz_timera/automator_api.py
omijacz_timera/omijacz_timera.py
omijacz_timera-0.4.1.dist-info/METADATA
omijacz_timera-0.4.1.dist-info/RECORD
omijacz_timera-0.4.1.dist-info/WHEEL
omijacz_timera-0.4.1.dist-info/dependency_links.txt
omijacz_timera-0.4.1.dist-info/entry_points.txt
omijacz_timera-0.4.1.dist-info/top_level.txt
omijacz_timera_prawojazdy/__init__.py
omijacz_timera_prawojazdy/automator.py
omijacz_timera_prawojazdy/automator_api.py
omijacz_timera_prawojazdy/execute.py
omijacz_timera_prawojazdy/omijacz_timera.py
omijacz_timera_prawojazdy/skeleton.py
