Metadata-Version: 2.1
Name: omijacz-timera
Version: 0.4.1
Summary: Skrypt omijający zbyt długi wymagany czas na slajd na stronie prawojazdy.com.pl
Home-page: http://github.com/taniotanio7/omijacz-timera-prawojazdy
Author: Jonatan Witoszek
Author-email: jonatanwitoszek@gmail.com
License: MIT
Platform: UNKNOWN
Classifier: License :: OSI Approved :: MIT License
Classifier: Programming Language :: Python
Classifier: Programming Language :: Python :: 3
Classifier: Programming Language :: Python :: 3.6
Classifier: Programming Language :: Python :: Implementation :: CPython
Classifier: Programming Language :: Python :: Implementation :: PyPy
Requires-Python: >=3.6.0
Requires-Dist: requests
Requires-Dist: splinter
Requires-Dist: docopt
